[
    {
        "Methods": "EventGLM_gwn",
        "Trigger_P": 70.4,
        "Trigger_R": 70.7,
        "Trigger_F1": 70.5,
        "Argument_P": 58.5,
        "Argument_R": 58.3,
        "Argument_F1": 58.4,
        "Triplet_P": 50.0,
        "Triplet_R": 50.2,
        "Triplet_F1": 50.2
    },
    {
        "Methods": "ST-Seq2SeqMRC",
        "Trigger_P": "-",
        "Trigger_R": "-",
        "Trigger_F1": "-",
        "Argument_P": 57.9,
        "Argument_R": 58.6,
        "Argument_F1": 58.2,
        "Triplet_P": 49.8,
        "Triplet_R": 50.1,
        "Triplet_F1": 49.9
    },
    {
        "Methods": "ST-SpanMRC",
        "Trigger_P": "-",
        "Trigger_R": "-",
        "Trigger_F1": "-",
        "Argument_P": 60.1,
        "Argument_R": 54.9,
        "Argument_F1": 57.4,
        "Triplet_P": 44.5,
        "Triplet_R": 44.8,
        "Triplet_F1": 44.7
    },
    {
        "Methods": "SeqTag",
        "Trigger_P": 69.5,
        "Trigger_R": 69.9,
        "Trigger_F1": 69.7,
        "Argument_P": 50.8,
        "Argument_R": 51.2,
        "Argument_F1": 51.0,
        "Triplet_P": 41.1,
        "Triplet_R": 41.3,
        "Triplet_F1": 41.2
    },
    {
        "Methods": "Unsuper",
        "Trigger_P": 21.0,
        "Trigger_R": 32.0,
        "Trigger_F1": 25.4,
        "Argument_P": 12.0,
        "Argument_R": 15.5,
        "Argument_F1": 13.5,
        "Triplet_P": 4.5,
        "Triplet_R": 6.8,
        "Triplet_F1": 5.4
    }
]
